README.md
setup.py
word2vec_keras/__init__.py
word2vec_keras/word2vec_keras.py
word2vec_keras.egg-info/PKG-INFO
word2vec_keras.egg-info/SOURCES.txt
word2vec_keras.egg-info/dependency_links.txt
word2vec_keras.egg-info/requires.txt
word2vec_keras.egg-info/top_level.txt