Metadata-Version: 2.1
Name: word2vec-keras
Version: 0.1
Summary: Word2Vec Keras Text Classifier
Home-page: https://github.com/javatechy/dokr
Author: Paolo Ripamonti
Author-email: paolo.ripamonti93@gmail.com
License: UNKNOWN
Keywords: keras,word2vec,deep learning,machine learning
Platform: UNKNOWN
Classifier: Programming Language :: Python :: 3
Classifier: License :: OSI Approved :: MIT License
Classifier: Operating System :: OS Independent
